odoo8_addon_base_business_document_import_phone-8.0.1.0.0.99.dev6-nspkg.pth
odoo_addons/base_business_document_import_phone/README.rst
odoo_addons/base_business_document_import_phone/__init__.py
odoo_addons/base_business_document_import_phone/__openerp__.py
odoo_addons/base_business_document_import_phone/i18n/base_business_document_import_phone.pot
odoo_addons/base_business_document_import_phone/models/__init__.py
odoo_addons/base_business_document_import_phone/models/business_document_import.py
odoo_addons/base_business_document_import_phone/static/description/icon.png
odoo_addons/base_business_document_import_phone/tests/__init__.py
odoo_addons/base_business_document_import_phone/tests/test_phone_partner_match.py
odoo8_addon_base_business_document_import_phone-8.0.1.0.0.99.dev6.dist-info/METADATA
odoo8_addon_base_business_document_import_phone-8.0.1.0.0.99.dev6.dist-info/WHEEL
odoo8_addon_base_business_document_import_phone-8.0.1.0.0.99.dev6.dist-info/namespace_packages.txt
odoo8_addon_base_business_document_import_phone-8.0.1.0.0.99.dev6.dist-info/top_level.txt
odoo8_addon_base_business_document_import_phone-8.0.1.0.0.99.dev6.dist-info/RECORD
